{
    "machine": "auto_infusion_matrix",
    "registryName": "auto_infusion_matrix_thaumcraft_VoidRobeLegs",
    "recipeTime": 44,
    "requirements": [
        {
            "type": "energy",
            "io-type": "input",
            "energyPerTick": 5000
        },
        {
            "type": "item",
            "io-type": "input",
            "item": "thaumcraft:plate@3",
            "amount": 2
        },
        {
            "type": "item",
            "io-type": "input",
            "item": "thaumcraft:cloth_legs"
        },
        {
            "type": "item",
            "io-type": "input",
            "item": "contenttweaker:magical_leather"
        },
        {
            "type": "item",
            "io-type": "input",
            "item": "thaumcraft:salis_mundus"
        },
        {
            "type": "item",
            "io-type": "input",
            "item": "thaumcraft:fabric"
        },
        {
            "type": "item",
            "io-type": "input",
            "item": "thaumcraft:void_legs"
        },
        {
            "type": "aspect",
            "io-type": "input",
            "aspect": "metallum",
            "amount": 50
        },
        {
            "type": "aspect",
            "io-type": "input",
            "aspect": "praemunio",
            "amount": 50
        },
        {
            "type": "aspect",
            "io-type": "input",
            "aspect": "vacuos",
            "amount": 50
        },
        {
            "type": "aspect",
            "io-type": "input",
            "aspect": "potentia",
            "amount": 35
        },
        {
            "type": "aspect",
            "io-type": "input",
            "aspect": "alienis",
            "amount": 35
        },
        {
            "type": "item",
            "io-type": "output",
            "item": "thaumcraft:void_robe_legs"
        }
    ]
}
